compas_rv2/__init__.py
compas_rv2/activate.py
compas_rv2/install.py
compas_rv2/uninstall.py
compas_rv2/datastructures/__init__.py
compas_rv2/datastructures/forcediagram.py
compas_rv2/datastructures/formdiagram.py
compas_rv2/datastructures/meshmixin.py
compas_rv2/datastructures/pattern.py
compas_rv2/datastructures/skeleton.py
compas_rv2/datastructures/subdmesh.py
compas_rv2/datastructures/thrustdiagram.py
compas_rv2/rhino/__init__.py
compas_rv2/rhino/helpers.py
compas_rv2/rhino/artists/__init__.py
compas_rv2/rhino/artists/forceartist.py
compas_rv2/rhino/artists/formartist.py
compas_rv2/rhino/artists/meshartist.py
compas_rv2/rhino/artists/skeletonartist.py
compas_rv2/rhino/artists/thrustartist.py
compas_rv2/rhino/conduits/__init__.py
compas_rv2/rhino/conduits/forceconduit.py
compas_rv2/rhino/conduits/horizontalconduit.py
compas_rv2/rhino/conduits/subdconduit.py
compas_rv2/rhino/conduits/thrustconduit.py
compas_rv2/rhino/forms/__init__.py
compas_rv2/rhino/forms/attributes.py
compas_rv2/rhino/forms/browser.py
compas_rv2/rhino/forms/error.py
compas_rv2/rhino/forms/menu.py
compas_rv2/rhino/forms/modifyattributes.py
compas_rv2/rhino/forms/settings.py
compas_rv2/rhino/forms/src/._background.png
compas_rv2/rhino/forms/src/background.png
compas_rv2/rhino/forms/src/index.html
compas_rv2/rhino/forms/src/rv2.png
compas_rv2/rhino/forms/src/styles.css
compas_rv2/rhino/objects/__init__.py
compas_rv2/rhino/objects/forceobject.py
compas_rv2/rhino/objects/formobject.py
compas_rv2/rhino/objects/meshobject.py
compas_rv2/rhino/objects/patternobject.py
compas_rv2/rhino/objects/skeletonobject.py
compas_rv2/rhino/objects/subdobject.py
compas_rv2/rhino/objects/thrustobject.py
compas_rv2/scene/__init__.py
compas_rv2/scene/scene.py
compas_rv2/singular/__init__.py
compas_rv2/singular/algorithms/__init__.py
compas_rv2/singular/algorithms/decomposition.py
compas_rv2/singular/algorithms/propagation.py
compas_rv2/singular/algorithms/triangulation.py
compas_rv2/singular/datastructures/__init__.py
compas_RV2-1.4.7.dist-info/AUTHORS.md
compas_RV2-1.4.7.dist-info/LICENSE
compas_RV2-1.4.7.dist-info/METADATA
compas_RV2-1.4.7.dist-info/WHEEL
compas_RV2-1.4.7.dist-info/entry_points.txt
compas_RV2-1.4.7.dist-info/top_level.txt
compas_RV2-1.4.7.dist-info/RECORD
