Metadata-Version: 2.1
Name: compas-RV2
Version: 1.4.7
Summary: RhinoVault for Rhino 6 based on COMPAS
Home-page: https://github.com/BlockResearchGroup/compas-RV2
Author: tom van mele
Author-email: van.mele@arch.ethz.ch
License: MIT license
Platform: UNKNOWN
Classifier: Development Status :: 4 - Beta
Classifier: Intended Audience :: Developers
Classifier: Topic :: Scientific/Engineering
Classifier: License :: OSI Approved :: MIT License
Classifier: Operating System :: Unix
Classifier: Operating System :: POSIX
Classifier: Operating System :: Microsoft :: Windows
Classifier: Programming Language :: Python
Classifier: Programming Language :: Python :: 3
Classifier: Programming Language :: Python :: 3.6
Classifier: Programming Language :: Python :: 3.7
Classifier: Programming Language :: Python :: 3.8
Classifier: Programming Language :: Python :: Implementation :: CPython
Requires-Python: >=3.6
License-File: LICENSE
License-File: AUTHORS.md
Requires-Dist: COMPAS (>=1.13.3)
Requires-Dist: compas-cloud (>=0.3.0)
Requires-Dist: compas-tna (>=0.1.5)
Requires-Dist: compas-skeleton (>=1.1.4)
